{
 "Labels": "Nighthawk 941d93f6_qps_1000_c_32_1024_mixer_both",
 "RequestedQPS": 1000,
 "ActualQPS": 999.99997654166725,
 "ActualDuration": 240000005630,
 "NumThreads": 32,
 "DurationHistogram": {
  "Count": "239999",
  "Data": [
   {
    "Start": 0.000726495,
    "End": 0.000726495,
    "Percent": 0,
    "Count": "1"
   },
   {
    "Start": 0.000726495,
    "End": 0.000817343,
    "Percent": 10,
    "Count": "24016"
   },
   {
    "Start": 0.000817343,
    "End": 0.000842815,
    "Percent": 20,
    "Count": "23987"
   },
   {
    "Start": 0.000842815,
    "End": 0.000865567,
    "Percent": 30,
    "Count": "24018"
   },
   {
    "Start": 0.000865567,
    "End": 0.000886687,
    "Percent": 40,
    "Count": "23991"
   },
   {
    "Start": 0.000886687,
    "End": 0.000922623,
    "Percent": 50,
    "Count": "24018"
   },
   {
    "Start": 0.000922623,
    "End": 0.000939871,
    "Percent": 55.000000000000007,
    "Count": "11983"
   },
   {
    "Start": 0.000939871,
    "End": 0.000959807,
    "Percent": 60,
    "Count": "11990"
   },
   {
    "Start": 0.000959807,
    "End": 0.000977599,
    "Percent": 65,
    "Count": "12008"
   },
   {
    "Start": 0.000977599,
    "End": 0.000997503,
    "Percent": 70,
    "Count": "11999"
   },
   {
    "Start": 0.000997503,
    "End": 0.001022047,
    "Percent": 75,
    "Count": "11993"
   },
   {
    "Start": 0.001022047,
    "End": 0.001035007,
    "Percent": 77.5,
    "Count": "6004"
   },
   {
    "Start": 0.001035007,
    "End": 0.001050943,
    "Percent": 80,
    "Count": "6000"
   },
   {
    "Start": 0.001050943,
    "End": 0.001064255,
    "Percent": 82.5,
    "Count": "5994"
   },
   {
    "Start": 0.001064255,
    "End": 0.001080703,
    "Percent": 85,
    "Count": "6022"
   },
   {
    "Start": 0.001080703,
    "End": 0.001097535,
    "Percent": 87.5,
    "Count": "5994"
   },
   {
    "Start": 0.001097535,
    "End": 0.001110015,
    "Percent": 88.75,
    "Count": "2999"
   },
   {
    "Start": 0.001110015,
    "End": 0.001127039,
    "Percent": 90,
    "Count": "2989"
   },
   {
    "Start": 0.001127039,
    "End": 0.001154367,
    "Percent": 91.25,
    "Count": "3000"
   },
   {
    "Start": 0.001154367,
    "End": 0.001192127,
    "Percent": 92.5,
    "Count": "2995"
   },
   {
    "Start": 0.001192127,
    "End": 0.001232127,
    "Percent": 93.75,
    "Count": "3002"
   },
   {
    "Start": 0.001232127,
    "End": 0.001255679,
    "Percent": 94.375,
    "Count": "1497"
   },
   {
    "Start": 0.001255679,
    "End": 0.001283135,
    "Percent": 95,
    "Count": "1503"
   },
   {
    "Start": 0.001283135,
    "End": 0.001316799,
    "Percent": 95.625,
    "Count": "1497"
   },
   {
    "Start": 0.001316799,
    "End": 0.001381503,
    "Percent": 96.25,
    "Count": "1502"
   },
   {
    "Start": 0.001381503,
    "End": 0.001602559,
    "Percent": 96.875,
    "Count": "1498"
   },
   {
    "Start": 0.001602559,
    "End": 0.001724543,
    "Percent": 97.1875,
    "Count": "750"
   },
   {
    "Start": 0.001724543,
    "End": 0.001807807,
    "Percent": 97.5,
    "Count": "750"
   },
   {
    "Start": 0.001807807,
    "End": 0.001890111,
    "Percent": 97.8125,
    "Count": "750"
   },
   {
    "Start": 0.001890111,
    "End": 0.002004863,
    "Percent": 98.125,
    "Count": "750"
   },
   {
    "Start": 0.002004863,
    "End": 0.002160127,
    "Percent": 98.4375,
    "Count": "750"
   },
   {
    "Start": 0.002160127,
    "End": 0.002296703,
    "Percent": 98.59375,
    "Count": "375"
   },
   {
    "Start": 0.002296703,
    "End": 0.002365695,
    "Percent": 98.75,
    "Count": "375"
   },
   {
    "Start": 0.002365695,
    "End": 0.002408831,
    "Percent": 98.90625,
    "Count": "375"
   },
   {
    "Start": 0.002408831,
    "End": 0.002450047,
    "Percent": 99.0625,
    "Count": "377"
   },
   {
    "Start": 0.002450047,
    "End": 0.002492287,
    "Percent": 99.21875,
    "Count": "373"
   },
   {
    "Start": 0.002492287,
    "End": 0.002514943,
    "Percent": 99.296875,
    "Count": "187"
   },
   {
    "Start": 0.002514943,
    "End": 0.002537599,
    "Percent": 99.375,
    "Count": "188"
   },
   {
    "Start": 0.002537599,
    "End": 0.002563455,
    "Percent": 99.453125,
    "Count": "187"
   },
   {
    "Start": 0.002563455,
    "End": 0.002591231,
    "Percent": 99.53125,
    "Count": "188"
   },
   {
    "Start": 0.002591231,
    "End": 0.002624895,
    "Percent": 99.609375,
    "Count": "187"
   },
   {
    "Start": 0.002624895,
    "End": 0.002649855,
    "Percent": 99.6484375,
    "Count": "95"
   },
   {
    "Start": 0.002649855,
    "End": 0.002678399,
    "Percent": 99.6875,
    "Count": "93"
   },
   {
    "Start": 0.002678399,
    "End": 0.002720895,
    "Percent": 99.7265625,
    "Count": "93"
   },
   {
    "Start": 0.002720895,
    "End": 0.002782463,
    "Percent": 99.765625,
    "Count": "94"
   },
   {
    "Start": 0.002782463,
    "End": 0.002894079,
    "Percent": 99.8046875,
    "Count": "94"
   },
   {
    "Start": 0.002894079,
    "End": 0.002963711,
    "Percent": 99.82421875,
    "Count": "47"
   },
   {
    "Start": 0.002963711,
    "End": 0.003036799,
    "Percent": 99.84375,
    "Count": "47"
   },
   {
    "Start": 0.003036799,
    "End": 0.003109375,
    "Percent": 99.86328125,
    "Count": "46"
   },
   {
    "Start": 0.003109375,
    "End": 0.003214207,
    "Percent": 99.8828125,
    "Count": "47"
   },
   {
    "Start": 0.003214207,
    "End": 0.003275775,
    "Percent": 99.90234375,
    "Count": "47"
   },
   {
    "Start": 0.003275775,
    "End": 0.003317887,
    "Percent": 99.912109375,
    "Count": "25"
   },
   {
    "Start": 0.003317887,
    "End": 0.003354239,
    "Percent": 99.921875,
    "Count": "22"
   },
   {
    "Start": 0.003354239,
    "End": 0.003388671,
    "Percent": 99.931640625,
    "Count": "23"
   },
   {
    "Start": 0.003388671,
    "End": 0.003453951,
    "Percent": 99.94140625,
    "Count": "24"
   },
   {
    "Start": 0.003453951,
    "End": 0.003496063,
    "Percent": 99.951171875,
    "Count": "23"
   },
   {
    "Start": 0.003496063,
    "End": 0.003512575,
    "Percent": 99.9560546875,
    "Count": "12"
   },
   {
    "Start": 0.003512575,
    "End": 0.003542015,
    "Percent": 99.9609375,
    "Count": "12"
   },
   {
    "Start": 0.003542015,
    "End": 0.003574399,
    "Percent": 99.9658203125,
    "Count": "11"
   },
   {
    "Start": 0.003574399,
    "End": 0.003618559,
    "Percent": 99.970703125,
    "Count": "12"
   },
   {
    "Start": 0.003618559,
    "End": 0.003654911,
    "Percent": 99.9755859375,
    "Count": "12"
   },
   {
    "Start": 0.003654911,
    "End": 0.003679743,
    "Percent": 99.97802734375,
    "Count": "6"
   },
   {
    "Start": 0.003679743,
    "End": 0.003730303,
    "Percent": 99.98046875,
    "Count": "6"
   },
   {
    "Start": 0.003730303,
    "End": 0.003774847,
    "Percent": 99.98291015625,
    "Count": "5"
   },
   {
    "Start": 0.003774847,
    "End": 0.003798399,
    "Percent": 99.9853515625,
    "Count": "6"
   },
   {
    "Start": 0.003798399,
    "End": 0.003934847,
    "Percent": 99.98779296875,
    "Count": "6"
   },
   {
    "Start": 0.003934847,
    "End": 0.004030463,
    "Percent": 99.989013671875,
    "Count": "3"
   },
   {
    "Start": 0.004030463,
    "End": 0.004051967,
    "Percent": 99.990234375,
    "Count": "3"
   },
   {
    "Start": 0.004051967,
    "End": 0.004089215,
    "Percent": 99.991455078125,
    "Count": "3"
   },
   {
    "Start": 0.004089215,
    "End": 0.004110975,
    "Percent": 99.99267578125,
    "Count": "3"
   },
   {
    "Start": 0.004110975,
    "End": 0.004119935,
    "Percent": 99.993896484375,
    "Count": "3"
   },
   {
    "Start": 0.004119935,
    "End": 0.004120575,
    "Percent": 99.9945068359375,
    "Count": "1"
   },
   {
    "Start": 0.004120575,
    "End": 0.004153215,
    "Percent": 99.9951171875,
    "Count": "2"
   },
   {
    "Start": 0.004153215,
    "End": 0.004157439,
    "Percent": 99.9957275390625,
    "Count": "1"
   },
   {
    "Start": 0.004157439,
    "End": 0.004229631,
    "Percent": 99.996337890625,
    "Count": "2"
   },
   {
    "Start": 0.004229631,
    "End": 0.004236031,
    "Percent": 99.9969482421875,
    "Count": "1"
   },
   {
    "Start": 0.004236031,
    "End": 0.004238335,
    "Percent": 99.99725341796875,
    "Count": "1"
   },
   {
    "Start": 0.004238335,
    "End": 0.004238591,
    "Percent": 99.99755859375,
    "Count": "1"
   },
   {
    "Start": 0.004238591,
    "End": 0.004238591,
    "Percent": 99.99786376953125,
    "Count": "0"
   },
   {
    "Start": 0.004238591,
    "End": 0.004263167,
    "Percent": 99.9981689453125,
    "Count": "1"
   },
   {
    "Start": 0.004263167,
    "End": 0.004372735,
    "Percent": 99.99847412109375,
    "Count": "1"
   },
   {
    "Start": 0.004372735,
    "End": 0.004372735,
    "Percent": 99.998626708984375,
    "Count": "0"
   },
   {
    "Start": 0.004372735,
    "End": 0.004414719,
    "Percent": 99.998779296875,
    "Count": "1"
   },
   {
    "Start": 0.004414719,
    "End": 0.004414719,
    "Percent": 99.998931884765625,
    "Count": "0"
   },
   {
    "Start": 0.004414719,
    "End": 0.004414719,
    "Percent": 99.99908447265625,
    "Count": "0"
   },
   {
    "Start": 0.004414719,
    "End": 0.004559615,
    "Percent": 99.999237060546875,
    "Count": "1"
   },
   {
    "Start": 0.004559615,
    "End": 0.004559615,
    "Percent": 99.999313354492188,
    "Count": "0"
   },
   {
    "Start": 0.004559615,
    "End": 0.004559615,
    "Percent": 99.9993896484375,
    "Count": "0"
   },
   {
    "Start": 0.004559615,
    "End": 0.004559615,
    "Percent": 99.999465942382812,
    "Count": "0"
   },
   {
    "Start": 0.004559615,
    "End": 0.004559615,
    "Percent": 99.999542236328125,
    "Count": "0"
   },
   {
    "Start": 0.004559615,
    "End": 0.004963327,
    "Percent": 99.999618530273438,
    "Count": "1"
   },
   {
    "Start": 0.004963327,
    "End": 0.004963327,
    "Percent": 100,
    "Count": "0"
   }
  ],
  "Min": 0.000726495,
  "Max": 0.004963327,
  "Sum": 236.105976221,
  "Avg": 0.000983779,
  "StdDev": 0.000263902,
  "Percentiles": [
   {
    "Percentile": 50,
    "Value": 0.000922623
   },
   {
    "Percentile": 75,
    "Value": 0.001022047
   },
   {
    "Percentile": 80,
    "Value": 0.001050943
   },
   {
    "Percentile": 90,
    "Value": 0.001127039
   },
   {
    "Percentile": 95,
    "Value": 0.001283135
   },
   {
    "Percentile": 99,
    "Value": 0.002450047
   },
   {
    "Percentile": 99.9,
    "Value": 0.003275775
   }
  ]
 },
 "RetCodes": {
  "200": "239999"
 },
 "URL": "http://fortioserver:8080/",
 "Version": "0.3.0",
 "Jitter": false,
 "RunType": "HTTP",
 "Sizes": {
  "Count": "239999",
  "Data": [],
  "Min": 1024,
  "Max": 1024,
  "Sum": 245758976,
  "Avg": 1024,
  "StdDev": 0,
  "Percentiles": []
 },
 "HeaderSizes": {
  "Count": "239999",
  "Data": [],
  "Min": 143,
  "Max": 143,
  "Sum": 34319857,
  "Avg": 143,
  "StdDev": 0,
  "Percentiles": []
 },
 "BytesSent": "29040000",
 "BytesReceived": "287998800",
 "StartTime": "2020-04-30T05:44:38.379416420Z",
 "RequestedDuration": "240s"
}
