{
  "RunType": "HTTP",
  "Labels": "ae2b966d_qps_1000_c_32_1024_none_both",
  "StartTime": "2020-04-19T06:01:51.7997611Z",
  "RequestedQPS": "1000",
  "RequestedDuration": "4m0s",
  "ActualQPS": 999.9828851137577,
  "ActualDuration": 240004107643,
  "NumThreads": 32,
  "Version": "1.3.2-pre",
  "DurationHistogram": {
    "Count": 240000,
    "Min": 0.000728978,
    "Max": 0.006612907,
    "Sum": 663.7959974359998,
    "Avg": 0.0027658166559833323,
    "StdDev": 0.0007874650412153604,
    "Data": [
      {
        "Start": 0.000728978,
        "End": 0.0008,
        "Percent": 0.0008333333333333334,
        "Count": 2
      },
      {
        "Start": 0.0008,
        "End": 0.0009000000000000001,
        "Percent": 0.005833333333333334,
        "Count": 12
      },
      {
        "Start": 0.0009000000000000001,
        "End": 0.001,
        "Percent": 0.04,
        "Count": 82
      },
      {
        "Start": 0.001,
        "End": 0.00125,
        "Percent": 1.0325,
        "Count": 2382
      },
      {
        "Start": 0.00125,
        "End": 0.0015,
        "Percent": 6.670833333333333,
        "Count": 13532
      },
      {
        "Start": 0.0015,
        "End": 0.00175,
        "Percent": 16.76125,
        "Count": 24217
      },
      {
        "Start": 0.00175,
        "End": 0.002,
        "Percent": 22.91125,
        "Count": 14760
      },
      {
        "Start": 0.002,
        "End": 0.0022500000000000003,
        "Percent": 27.74125,
        "Count": 11592
      },
      {
        "Start": 0.0022500000000000003,
        "End": 0.0025,
        "Percent": 35.026666666666664,
        "Count": 17485
      },
      {
        "Start": 0.0025,
        "End": 0.003,
        "Percent": 52.77875,
        "Count": 42605
      },
      {
        "Start": 0.003,
        "End": 0.0035,
        "Percent": 82.27791666666667,
        "Count": 70798
      },
      {
        "Start": 0.0035,
        "End": 0.004,
        "Percent": 97.20375,
        "Count": 35822
      },
      {
        "Start": 0.004,
        "End": 0.0045000000000000005,
        "Percent": 99.65791666666667,
        "Count": 5890
      },
      {
        "Start": 0.0045000000000000005,
        "End": 0.005,
        "Percent": 99.965,
        "Count": 737
      },
      {
        "Start": 0.005,
        "End": 0.006,
        "Percent": 99.99625,
        "Count": 75
      },
      {
        "Start": 0.006,
        "End": 0.006612907,
        "Percent": 100,
        "Count": 9
      }
    ],
    "Percentiles": [
      {
        "Percentile": 50,
        "Value": 0.0029217345381997418
      },
      {
        "Percentile": 75,
        "Value": 0.0033766419955365973
      },
      {
        "Percentile": 90,
        "Value": 0.003758681815644018
      },
      {
        "Percentile": 99,
        "Value": 0.004365959252971138
      },
      {
        "Percentile": 99.9,
        "Value": 0.004894165535956586
      }
    ]
  },
  "Exactly": 0,
  "Jitter": false,
  "RetCodes": {
    "200": 240000
  },
  "Sizes": {
    "Count": 240000,
    "Min": 1191,
    "Max": 1191,
    "Sum": 285840000,
    "Avg": 1191,
    "StdDev": 0,
    "Data": [
      {
        "Start": 1191,
        "End": 1191,
        "Percent": 100,
        "Count": 240000
      }
    ],
    "Percentiles": null
  },
  "HeaderSizes": {
    "Count": 240000,
    "Min": 167,
    "Max": 167,
    "Sum": 40080000,
    "Avg": 167,
    "StdDev": 0,
    "Data": [
      {
        "Start": 167,
        "End": 167,
        "Percent": 100,
        "Count": 240000
      }
    ],
    "Percentiles": null
  },
  "URL": "http://fortioserver:8080/echo?size=1024",
  "SocketCount": 32,
  "AbortOn": 0
}
